lst/__init__.py
lst/futures.py
lst/scrape.py
lst-0.2.11.dist-info/LICENSE
lst-0.2.11.dist-info/METADATA
lst-0.2.11.dist-info/WHEEL
lst-0.2.11.dist-info/top_level.txt
lst-0.2.11.dist-info/RECORD
