Metadata-Version: 1.2
Name: lst
Version: 0.2.11
Summary: Declarative Scraping Tools
Home-page: UNKNOWN
Author: Andriy Stremeluk
Author-email: astremeluk@gmail.com
License: MIT
Platform: UNKNOWN
Classifier: Programming Language :: Python :: 3
Classifier: License :: OSI Approved :: MIT License
Classifier: Operating System :: OS Independent
Requires-Python: >=3.5
